BanzaiDB/__init__.py
BanzaiDB/BanzaiDB
BanzaiDB/banzaidb.py
BanzaiDB/config.py
BanzaiDB/converters.py
BanzaiDB/core.py
BanzaiDB/database.py
BanzaiDB/errors.py
BanzaiDB/fetch.py
BanzaiDB/imaging.py
BanzaiDB/mapping.py
BanzaiDB/misc.py
BanzaiDB/parsers.py
BanzaiDB/fabfile/__init__.py
BanzaiDB/fabfile/variants.py
BanzaiDB-0.3.0.data/data/LICENSE
BanzaiDB-0.3.0.data/data/README.rst
BanzaiDB-0.3.0.data/data/requirements.txt
BanzaiDB-0.3.0.data/data/docs/BanzaiDB.fabfile.html
BanzaiDB-0.3.0.data/data/docs/BanzaiDB.html
BanzaiDB-0.3.0.data/data/docs/developer.html
BanzaiDB-0.3.0.data/data/docs/genindex.html
BanzaiDB-0.3.0.data/data/docs/getting-metadata-into-banzaiDB.html
BanzaiDB-0.3.0.data/data/docs/index.html
BanzaiDB-0.3.0.data/data/docs/init.html
BanzaiDB-0.3.0.data/data/docs/installation.html
BanzaiDB-0.3.0.data/data/docs/modules.html
BanzaiDB-0.3.0.data/data/docs/objects.inv
BanzaiDB-0.3.0.data/data/docs/py-modindex.html
BanzaiDB-0.3.0.data/data/docs/search.html
BanzaiDB-0.3.0.data/data/docs/searchindex.js
BanzaiDB-0.3.0.data/data/docs/tables.html
BanzaiDB-0.3.0.data/data/docs/_sources/BanzaiDB.fabfile.txt
BanzaiDB-0.3.0.data/data/docs/_sources/BanzaiDB.txt
BanzaiDB-0.3.0.data/data/docs/_sources/developer.txt
BanzaiDB-0.3.0.data/data/docs/_sources/getting-metadata-into-banzaiDB.txt
BanzaiDB-0.3.0.data/data/docs/_sources/index.html
BanzaiDB-0.3.0.data/data/docs/_sources/index.txt
BanzaiDB-0.3.0.data/data/docs/_sources/init.txt
BanzaiDB-0.3.0.data/data/docs/_sources/installation.txt
BanzaiDB-0.3.0.data/data/docs/_sources/modules.txt
BanzaiDB-0.3.0.data/data/docs/_sources/tables.txt
BanzaiDB-0.3.0.data/data/docs/_static/ajax-loader.gif
BanzaiDB-0.3.0.data/data/docs/_static/basic.css
BanzaiDB-0.3.0.data/data/docs/_static/comment-bright.png
BanzaiDB-0.3.0.data/data/docs/_static/comment-close.png
BanzaiDB-0.3.0.data/data/docs/_static/comment.png
BanzaiDB-0.3.0.data/data/docs/_static/default.css
BanzaiDB-0.3.0.dist-info/DESCRIPTION.rst
BanzaiDB-0.3.0.dist-info/METADATA
BanzaiDB-0.3.0.dist-info/metadata.json
BanzaiDB-0.3.0.dist-info/RECORD
BanzaiDB-0.3.0.dist-info/top_level.txt
BanzaiDB-0.3.0.dist-info/WHEEL
