Metadata-Version: 2.0
Name: BanzaiDB
Version: 0.3.0
Summary: Database for Banzai NGS pipeline tool
Home-page: http://github.com/mscook/BanzaiDB
Author: Mitchell Stanton-Cook
Author-email: m.stantoncook@gmail.com
License: ECL 2.0
Platform: UNKNOWN
Classifier: Development Status :: 3 - Alpha
Classifier: Environment :: Console
Classifier: Intended Audience :: Science/Research
Classifier: License :: OSI Approved
Classifier: Natural Language :: English
Classifier: Operating System :: POSIX :: Linux
Classifier: Programming Language :: Python
Classifier: Programming Language :: Python :: 2.7
Classifier: Programming Language :: Python :: 2 :: Only
Classifier: Topic :: Scientific/Engineering :: Bio-Informatics
Requires-Dist: reportlab
Requires-Dist: rethinkdb
Requires-Dist: biopython
Requires-Dist: fabric
Requires-Dist: tablib
Requires-Dist: argparse
